pydplace/__init__.py
pydplace/__main__.py
pydplace/cross_dataset_ids.json
pydplace/dataset.py
pydplace/geo.py
pydplace/glottolog.py
pydplace/scaffold.py
pydplace/util.py
pydplace/wgsrpd_level2.geojson
pydplace/commands/__init__.py
pydplace/commands/check.py
pydplace/commands/glottolog.py
pydplace/commands/glottologbib.py
pydplace/commands/release.py
pydplace/dataset_template/CONTRIBUTORS.md_tmpl
pydplace/dataset_template/RELEASING.md_tmpl
pydplace/dataset_template/cldfbench_+id+.py_tmpl
pydplace/dataset_template/setup.cfg
pydplace/dataset_template/setup.py_tmpl
pydplace/dataset_template/test.py
pydplace/dataset_template/.github/workflows/cldf-validation.yml
pydplace-3.2.1.dist-info/licenses/LICENSE
pydplace-3.2.1.dist-info/METADATA
pydplace-3.2.1.dist-info/WHEEL
pydplace-3.2.1.dist-info/entry_points.txt
pydplace-3.2.1.dist-info/top_level.txt
pydplace-3.2.1.dist-info/RECORD
